pydataclasses/__init__.py
pydataclasses/data.py
pydataclasses/utils.py
pydataclasses-1.0.2.dist-info/LICENSE
pydataclasses-1.0.2.dist-info/METADATA
pydataclasses-1.0.2.dist-info/WHEEL
pydataclasses-1.0.2.dist-info/top_level.txt
pydataclasses-1.0.2.dist-info/RECORD
